langchain_pangu/__init__.py
langchain_pangu/chat_models.py
langchain_pangu/embeddings.py
langchain_pangu/llm_config.py
langchain_pangu/llms.py
langchain_pangu/tool_calls.py
langchain_pangu/utils.py
langchain_pangu/pangukitsappdev/__init__.py
langchain_pangu/pangukitsappdev/agent/__init__.py
langchain_pangu/pangukitsappdev/agent/agent_action.py
langchain_pangu/pangukitsappdev/agent/agent_session.py
langchain_pangu/pangukitsappdev/agent/react_agent.py
langchain_pangu/pangukitsappdev/agent/react_pangu_agent.py
langchain_pangu/pangukitsappdev/api/__init__.py
langchain_pangu/pangukitsappdev/api/common_config.py
langchain_pangu/pangukitsappdev/api/config_loader.py
langchain_pangu/pangukitsappdev/api/crypto_util.py
langchain_pangu/pangukitsappdev/api/schema.py
langchain_pangu/pangukitsappdev/api/agent/__init__.py
langchain_pangu/pangukitsappdev/api/agent/base.py
langchain_pangu/pangukitsappdev/api/doc_split/__init__.py
langchain_pangu/pangukitsappdev/api/doc_split/base.py
langchain_pangu/pangukitsappdev/api/doc_split/factory.py
langchain_pangu/pangukitsappdev/api/doc_split/split_config.py
langchain_pangu/pangukitsappdev/api/embeddings/__init__.py
langchain_pangu/pangukitsappdev/api/embeddings/base.py
langchain_pangu/pangukitsappdev/api/embeddings/embedding_config.py
langchain_pangu/pangukitsappdev/api/embeddings/factory.py
langchain_pangu/pangukitsappdev/api/llms/__init__.py
langchain_pangu/pangukitsappdev/api/llms/base.py
langchain_pangu/pangukitsappdev/api/llms/factory.py
langchain_pangu/pangukitsappdev/api/llms/llm_config.py
langchain_pangu/pangukitsappdev/api/memory/__init__.py
langchain_pangu/pangukitsappdev/api/memory/message_history_config.py
langchain_pangu/pangukitsappdev/api/memory/cache/__init__.py
langchain_pangu/pangukitsappdev/api/memory/cache/base.py
langchain_pangu/pangukitsappdev/api/memory/cache/cache_config.py
langchain_pangu/pangukitsappdev/api/memory/cache/factory.py
langchain_pangu/pangukitsappdev/api/memory/vector/__init__.py
langchain_pangu-0.3.7.dist-info/LICENSE
langchain_pangu-0.3.7.dist-info/METADATA
langchain_pangu-0.3.7.dist-info/WHEEL
langchain_pangu-0.3.7.dist-info/top_level.txt
langchain_pangu-0.3.7.dist-info/RECORD
