Metadata-Version: 2.1
Name: langchain-pangu
Version: 0.3.7
Summary: langchain-pangu
Author-email: MeiK <meik2333@gmail.com>
Project-URL: Homepage, https://github.com/MeiK2333/langchain-pangu
Project-URL: Issues, https://github.com/MeiK2333/langchain-pangu/issues
Classifier: Programming Language :: Python :: 3
Classifier: License :: OSI Approved :: MIT License
Classifier: Operating System :: OS Independent
Requires-Python: >=3.8
License-File: LICENSE
Requires-Dist: langchain<0.4,>=0.3
Requires-Dist: langchain-community<0.4,>=0.3
Requires-Dist: langgraph<0.3,>=0.2.20
Requires-Dist: langchain_openai<0.3,>=0.2
Requires-Dist: jinja2
Requires-Dist: httpx
Requires-Dist: h2<5,>=3
Requires-Dist: pydantic<3,>=2
Requires-Dist: pydantic-settings<3,>=2
